MANIFEST.in
README.md
fake_useragxxx.c
fake_useragxxx.py
pyproject.toml
setup.py
fake_useragxxx.egg-info/PKG-INFO
fake_useragxxx.egg-info/SOURCES.txt
fake_useragxxx.egg-info/dependency_links.txt
fake_useragxxx.egg-info/top_level.txt