Metadata-Version: 2.4
Name: fake_useragxxx
Version: 0.0.4
Summary: Fake User-Agent Generator with Gray Randomization
Author: Anonymous
Author-email: Anonymous <m00263277@gmail.com>
Requires-Python: >=3.7
Dynamic: author
Dynamic: requires-python
